KucoinOBM/OBM.py
KucoinOBM/__init__.py
KucoinOBM-0.0.1.dist-info/LICENSE
KucoinOBM-0.0.1.dist-info/METADATA
KucoinOBM-0.0.1.dist-info/WHEEL
KucoinOBM-0.0.1.dist-info/top_level.txt
KucoinOBM-0.0.1.dist-info/RECORD
