Metadata-Version: 2.1
Name: KucoinOBM
Version: 0.0.1
Summary: A reliable and fast kucoin orderbook maintainer and manager.
Home-page: https://www.github.com/PrivatePandaCO/KucoinOBM
Author: Parth Mittal
Author-email: parth@privatepanda.co
License: GNU GENERAL PUBLIC LICENSE Version 2
Project-URL: Documentation, https://github.com/PrivatePandaCO/KucoinOBM/blob/master/README.md
Project-URL: Github, https://github.com/PrivatePandaCO/KucoinOBM
License-File: LICENSE
Requires-Dist: orjson
Requires-Dist: requests
Requires-Dist: pyloggor
Requires-Dist: KucoinWrapper
